MetaProfile/MetaProfiler.py
MetaProfile/Profile.py
MetaProfile/Signal.py
MetaProfile/Window.py
MetaProfile/__init__.py
MetaProfile/utils.py
MetaProfile-0.1.0.dist-info/DESCRIPTION.rst
MetaProfile-0.1.0.dist-info/METADATA
MetaProfile-0.1.0.dist-info/RECORD
MetaProfile-0.1.0.dist-info/WHEEL
MetaProfile-0.1.0.dist-info/metadata.json
MetaProfile-0.1.0.dist-info/top_level.txt
